codexasi/__init__.py
codexasi/client.py
codexasi/permissions.py
codexasi-1.0.0.dist-info/METADATA
codexasi-1.0.0.dist-info/WHEEL
codexasi-1.0.0.dist-info/top_level.txt
codexasi-1.0.0.dist-info/RECORD
