Metadata-Version: 2.4
Name: codexasi
Version: 1.0.0
Summary: CodexASI SDK client
Author-email: CodexASI <dev@codexasi.ai>
License: Proprietary. All rights reserved.
Requires-Python: >=3.10
